[
    {
        "title": "cafe",
        "precio": 500,
        "id": 1,
        "url": "https://picsum.photos/id/0/600"
    },
    {
        "title": "cigarros",
        "precio": 500,
        "id": 2,
        "url": "https://picsum.photos/id/1/600"
    },
    {
        "title": "sombrero",
        "precio": 500,
        "id": 3,
        "url": "https://picsum.photos/id/2/600"
    },
    {
        "title": "soda",
        "precio": 500,
        "id": 4,
        "url": "https://picsum.photos/id/3/600"
    },
    {
        "title": "shampoo",
        "precio": 500,
        "id": 5,
        "url": "https://picsum.photos/id/4/600"
    },
    {
        "title": "audifonos",
        "precio": 500,
        "id": 6,
        "url": "https://picsum.photos/id/5/600"
    },
    {
        "title": "doritos",
        "precio": 500,
        "id": 7,
        "url": "https://picsum.photos/id/6/600"
    },
    {
        "title": "chocolate",
        "precio": 500,
        "id": 8,
        "url": "https://picsum.photos/id/7/600"
    },
    {
        "title": "pizza",
        "precio": 500,
        "id": 9,
        "url": "https://picsum.photos/id/8/600"
    },
    {
        "title": "ok",
        "precio": 500,
        "id": 10,
        "url": "https://picsum.photos/id/9/600"
    }
]